ycecream/__init__.py
ycecream/ycecream.py
ycecream-1.3.20.dist-info/METADATA
ycecream-1.3.20.dist-info/WHEEL
ycecream-1.3.20.dist-info/license.txt
ycecream-1.3.20.dist-info/top_level.txt
ycecream-1.3.20.dist-info/RECORD
