Metadata-Version: 2.1
Name: ycecream
Version: 1.3.20
Summary: ycecream - sweeter debugging and benchmarking
Author-email: Ruud van der Ham <rt.van.der.ham@gmail.com>
Project-URL: Homepage, https://github.com/salabim/ycecream
Project-URL: Repository, https://github.com/salabim/ycecream
Classifier: Development Status :: 5 - Production/Stable
Classifier: License :: OSI Approved :: MIT License
Classifier: Programming Language :: Python :: 3 :: Only
Requires-Python: >=3.6
License-File: license.txt
